pyhere/__init__.py
pyhere/pyhere.py
pyhere-1.0.3.dist-info/LICENSE
pyhere-1.0.3.dist-info/METADATA
pyhere-1.0.3.dist-info/WHEEL
pyhere-1.0.3.dist-info/top_level.txt
pyhere-1.0.3.dist-info/RECORD
