Metadata-Version: 2.1
Name: pyhere
Version: 1.0.3
Summary: Load files easily using relative path names and simple heuristics
Author-email: "Josh P. Sawyer" <josh@joshpsawyer.com>
License: MIT License
Project-URL: Documentation, https://wildland-creative.github.io/pyhere/
Project-URL: Repository, https://github.com/wildland-creative/pyhere
Project-URL: Changelog, https://github.com/wildland-creative/pyhere/blob/master/CHANGELOG.md
Classifier: Intended Audience :: Science/Research
Classifier: Programming Language :: Python :: 2.7
Classifier: Programming Language :: Python :: 3
Classifier: Programming Language :: Python :: 3.6
Classifier: License :: OSI Approved :: MIT License
Requires-Python: >=2.7
License-File: LICENSE
